worklab/__init__.py
worklab/ana.py
worklab/com.py
worklab/imu.py
worklab/kin.py
worklab/move.py
worklab/physio.py
worklab/plots.py
worklab/utils.py
worklab-2.1.1.dist-info/licenses/LICENSE
worklab-2.1.1.dist-info/METADATA
worklab-2.1.1.dist-info/WHEEL
worklab-2.1.1.dist-info/top_level.txt
worklab-2.1.1.dist-info/RECORD
