Metadata-Version: 2.4
Name: worklab
Version: 2.1.1
Summary: Basic scripts for worklab devices
Author-email: Sophie de Klerk <r.de.klerk@pl.hanze.nl>, Thomas Rietveld <t.rietveld@lboro.ac.uk>, Rowie Janssen <r.j.f.janssen@umcg.nl>, Jelmer Braaksma <j.braaksma01@umcg.nl>
License:                     GNU GENERAL PUBLIC LICENSE
Project-URL: Homepage, https://github.com/sophiedkk/worklab
Project-URL: Bug Reports, https://github.com/sophiedkk/worklab/issues
Keywords: biomechanics,ergometry,physiology
Classifier: Intended Audience :: Science/Research
Classifier: License :: OSI Approved :: GNU General Public License v3 (GPLv3)
Classifier: Programming Language :: Python :: 3
Classifier: Operating System :: OS Independent
Requires-Python: >=3.7
License-File: LICENSE
Requires-Dist: scipy>=1.2.0
Requires-Dist: numpy
Requires-Dist: pandas
Requires-Dist: matplotlib
Requires-Dist: xlrd
Requires-Dist: scikit-learn
Requires-Dist: seaborn
Provides-Extra: dev
Requires-Dist: pytest; extra == "dev"
Requires-Dist: Flake8-pyproject; extra == "dev"
Requires-Dist: black; extra == "dev"
Requires-Dist: jupyter-book; extra == "dev"
Requires-Dist: build; extra == "dev"
Dynamic: license-file
